aiomemoizettl.py
aiomemoizettl-0.0.3.dist-info/LICENSE
aiomemoizettl-0.0.3.dist-info/METADATA
aiomemoizettl-0.0.3.dist-info/WHEEL
aiomemoizettl-0.0.3.dist-info/top_level.txt
aiomemoizettl-0.0.3.dist-info/RECORD
