Metadata-Version: 2.1
Name: aiomemoizettl
Version: 0.0.3
Summary: Memoize asyncio Python calls with a per-result TTL
Home-page: https://github.com/michalc/aiomemoizettl
Author: Michal Charemza
Author-email: michal@charemza.name
License: UNKNOWN
Platform: UNKNOWN
Classifier: Programming Language :: Python :: 3
Classifier: License :: OSI Approved :: MIT License
Classifier: Operating System :: OS Independent
Classifier: Framework :: AsyncIO
Requires-Python: ~=3.5
